mergely/__init__.py
mergely/mergely.py
mergely-0.1.8.dist-info/METADATA
mergely-0.1.8.dist-info/WHEEL
mergely-0.1.8.dist-info/top_level.txt
mergely-0.1.8.dist-info/RECORD
